tmktprocess/__init__.py
tmktprocess/async_process.py
tmktprocess/process.py
tmktprocess-1.0.2.dist-info/METADATA
tmktprocess-1.0.2.dist-info/WHEEL
tmktprocess-1.0.2.dist-info/LICENSE
tmktprocess-1.0.2.dist-info/RECORD
