Metadata-Version: 2.1
Name: tmktprocess
Version: 1.0.2
Summary: An easyful thread runner
License: Apache 2.0
Author: ladettanguy
Author-email: sti2dlab.ladettanguy@gmail.com
Requires-Python: >=3.10,<4.0
Classifier: License :: Other/Proprietary License
Classifier: Programming Language :: Python :: 3
Classifier: Programming Language :: Python :: 3.10
Classifier: Programming Language :: Python :: 3.11
